pranjul_library/__init__.py
pranjul_library/main.py
pranjul_library-0.1.0.dist-info/METADATA
pranjul_library-0.1.0.dist-info/WHEEL
pranjul_library-0.1.0.dist-info/top_level.txt
pranjul_library-0.1.0.dist-info/RECORD
