Metadata-Version: 2.1
Name: pranjul_library
Version: 0.1.0
Summary: A library for returning string with alternate alphabates
Home-page: UNKNOWN
Author: Pranjul Shukla
Author-email: spranjul2592@gmail.com
License: UNKNOWN
Platform: UNKNOWN
Classifier: Programming Language :: Python :: 3
Classifier: License :: OSI Approved :: MIT License
Classifier: Operating System :: OS Independent
Requires-Python: >=3.6
